move_data/__init__.py
move_data/move_data.py
move_data/setup.py
move_data-0.1.7.dist-info/METADATA
move_data-0.1.7.dist-info/WHEEL
move_data-0.1.7.dist-info/top_level.txt
move_data-0.1.7.dist-info/RECORD
