Metadata-Version: 2.4
Name: move-data
Version: 0.1.7
Summary: A Python package for moving data between Google Sheets, SharePoint, Google Cloud Storage, and Snowflake
Home-page: https://github.com/yourusername/move-data
Author: Your Name
Author-email: Your Name <your.email@example.com>
License: MIT
Project-URL: Homepage, https://github.com/yourusername/move-data
Project-URL: Documentation, https://github.com/yourusername/move-data#readme
Project-URL: Repository, https://github.com/yourusername/move-data
Project-URL: Issues, https://github.com/yourusername/move-data/issues
Keywords: data,etl,snowflake,google-sheets,sharepoint,google-cloud-storage
Classifier: Development Status :: 4 - Beta
Classifier: Intended Audience :: Developers
Classifier: License :: OSI Approved :: MIT License
Classifier: Programming Language :: Python :: 3
Classifier: Programming Language :: Python :: 3.7
Classifier: Programming Language :: Python :: 3.8
Classifier: Programming Language :: Python :: 3.9
Classifier: Programming Language :: Python :: 3.10
Classifier: Programming Language :: Python :: 3.11
Requires-Python: >=3.7
Requires-Dist: requests>=2.25.0
Requires-Dist: pandas>=1.3.0
Requires-Dist: pygsheets>=2.0.0
Requires-Dist: snowflake-connector-python>=2.7.0
Requires-Dist: google-cloud-storage>=2.0.0
Requires-Dist: chardet>=4.0.0
Requires-Dist: openpyxl>=3.0.0
Dynamic: author
Dynamic: home-page
Dynamic: requires-python
